liberate/liberate.py
liberate-0.1.9.data/scripts/liberate
liberate-0.1.9.dist-info/COPYING
liberate-0.1.9.dist-info/LICENSE.txt
liberate-0.1.9.dist-info/METADATA
liberate-0.1.9.dist-info/WHEEL
liberate-0.1.9.dist-info/top_level.txt
liberate-0.1.9.dist-info/RECORD
