Metadata-Version: 2.1
Name: liberate
Version: 0.1.9
Summary: Video/Audio/Url liberation (to .ogg)
Home-page: https://notabug.org/necklace/liberate
Author: Nichlas Severinsen
Author-email: ns@nsz.no
License: UNKNOWN
Platform: UNKNOWN
Requires-Dist: youtube-dl
Requires-Dist: colorama
